odoo8_addon_donation_stay-8.0.0.1.0-py2.7-nspkg.pth
odoo_addons/donation_stay/donation_stay_data.xml
odoo_addons/donation_stay/__openerp__.py
odoo_addons/donation_stay/__init__.py
odoo_addons/donation_stay/README.rst
odoo_addons/donation_stay/stay_view.xml
odoo_addons/donation_stay/i18n/fr.po
odoo_addons/donation_stay/i18n/donation_stay.pot
odoo_addons/donation_stay/wizard/create_donation_stay_view.xml
odoo_addons/donation_stay/wizard/create_donation_stay.py
odoo_addons/donation_stay/wizard/__init__.py
odoo_addons/donation_stay/test/donate_from_stay.yml
odoo_addons/donation_stay/static/description/icon.png
odoo8_addon_donation_stay-8.0.0.1.0.dist-info/top_level.txt
odoo8_addon_donation_stay-8.0.0.1.0.dist-info/WHEEL
odoo8_addon_donation_stay-8.0.0.1.0.dist-info/RECORD
odoo8_addon_donation_stay-8.0.0.1.0.dist-info/metadata.json
odoo8_addon_donation_stay-8.0.0.1.0.dist-info/DESCRIPTION.rst
odoo8_addon_donation_stay-8.0.0.1.0.dist-info/METADATA
odoo8_addon_donation_stay-8.0.0.1.0.dist-info/namespace_packages.txt
